Metadata-Version: 2.4
Name: phonexia-audio-quality-estimation-client
Version: 2.0.2
Summary: Audio Quality Estimation Client
Author-email: Phonexia <info@phonexia.com>
Keywords: grpc,voice,voice-biometry,speech,age,estimation,age estimation
Requires-Python: >=3.9
Requires-Dist: more-itertools>=10.6.0
Requires-Dist: phonexia-grpc>=2.27.1
Requires-Dist: numpy>=2.0.0; python_version >= "3.12"
Requires-Dist: numpy<2.0.0; python_version < "3.12"
Requires-Dist: typer>=0.16.0
Requires-Dist: soundfile>=0.13.0
Requires-Dist: py-ubjson>=0.16.1
